pytictri/__init__.py
pytictri/const.py
pytictri/scanner.py
pytictri/teleinfo.py
pytictri-2.0.4.dist-info/LICENSE
pytictri-2.0.4.dist-info/METADATA
pytictri-2.0.4.dist-info/WHEEL
pytictri-2.0.4.dist-info/top_level.txt
pytictri-2.0.4.dist-info/RECORD
