Metadata-Version: 2.1
Name: pytictri
Version: 2.0.4
Summary: Teleinfo tri python library
Home-page: https://github.com/biker91620/pytictri/tree/master
Author: benblrm
License: GPL-3
Keywords: rest,pytictri,pyticcom,linky,tic,io,smart-things,iot
Platform: UNKNOWN
Classifier: Programming Language :: Python
Classifier: Development Status :: 5 - Production/Stable
Classifier: License :: OSI Approved :: GNU General Public License v3 or later (GPLv3+)
Classifier: Programming Language :: Python :: 3
Classifier: Programming Language :: Python :: 3.5
Classifier: Programming Language :: Python :: 3.6
Classifier: Programming Language :: Python :: 3.7
Classifier: Intended Audience :: Developers
Classifier: Intended Audience :: System Administrators
Classifier: Topic :: Home Automation
Requires-Dist: requests (>=2)
